lightmotif-0.10.0.dist-info/METADATA
lightmotif-0.10.0.dist-info/WHEEL
lightmotif-0.10.0.dist-info/licenses/COPYING
lightmotif/__init__.py
lightmotif/io.rs
lightmotif/lib.cp312-win_amd64.pyd
lightmotif/lib.pyi
lightmotif/lib.rs
lightmotif/py.typed
lightmotif/pyfile.rs
lightmotif/tests/__init__.py
lightmotif/tests/test_doctest.py
lightmotif/tests/test_load.py
lightmotif/tests/test_pipeline.py
lightmotif/tests/test_pvalue.py
lightmotif/tests/test_scanner.py
lightmotif/tests/test_sequence.py
lightmotif/tests/unittest.rs
lightmotif-0.10.0.dist-info/RECORD
