Metadata-Version: 2.4
Name: lightmotif
Version: 0.10.0
Classifier: Development Status :: 3 - Alpha
Classifier: Intended Audience :: Developers
Classifier: Intended Audience :: Science/Research
Classifier: License :: OSI Approved :: MIT License
Classifier: Operating System :: OS Independent
Classifier: Programming Language :: Rust
Classifier: Programming Language :: Python :: 3.7
Classifier: Programming Language :: Python :: 3.8
Classifier: Programming Language :: Python :: 3.9
Classifier: Programming Language :: Python :: 3.10
Classifier: Programming Language :: Python :: 3.11
Classifier: Programming Language :: Python :: 3.12
Classifier: Programming Language :: Python :: 3.13
Classifier: Programming Language :: Python :: Implementation :: CPython
Classifier: Programming Language :: Python :: Implementation :: PyPy
Classifier: Topic :: Scientific/Engineering :: Bio-Informatics
Classifier: Topic :: Scientific/Engineering :: Medical Science Apps.
Classifier: Topic :: Software Development :: Libraries :: Python Modules
Classifier: Typing :: Typed
License-File: COPYING
Summary: PyO3 bindings and Python interface to lightmotif, a library for platform-accelerated biological motif scanning using position weight matrices.
Keywords: bioinformatics,genomics,motif,pssm,matrix
Home-Page: https://github.com/althonos/lightmotif/tree/main/lightmotif-py
Author: Martin Larralde <martin.larralde@embl.de>
Author-email: Martin Larralde <martin.larralde@embl.de>
License: MIT OR GPL-3.0-or-later
Requires-Python: >=3.7
Project-URL: Homepage, https://github.com/althonos/lightmotif/
Project-URL: Bug Tracker, https://github.com/althonos/lightmotif/issues
Project-URL: Changelog, https://github.com/althonos/lightmotif/blob/master/CHANGELOG.md
Project-URL: Coverage, https://codecov.io/gh/althonos/lightmotif/
Project-URL: Documentation, https://lightmotif.readthedocs.io/
Project-URL: Builds, https://github.com/althonos/lightmotif/actions/
Project-URL: PyPI, https://pypi.org/project/lightmotif
